pywe_event_message/__init__.py
pywe_event_message/eventmsg.py
pywe_event_message-1.0.1.dist-info/DESCRIPTION.rst
pywe_event_message-1.0.1.dist-info/METADATA
pywe_event_message-1.0.1.dist-info/RECORD
pywe_event_message-1.0.1.dist-info/WHEEL
pywe_event_message-1.0.1.dist-info/metadata.json
pywe_event_message-1.0.1.dist-info/top_level.txt
